imio.events.policy-1.1.7-py3.12-nspkg.pth
imio/events/policy/__init__.py
imio/events/policy/configure.zcml
imio/events/policy/interfaces.py
imio/events/policy/permissions.zcml
imio/events/policy/setuphandlers.py
imio/events/policy/subscribers.zcml
imio/events/policy/testing.py
imio/events/policy/utils.py
imio/events/policy/browser/__init__.py
imio/events/policy/browser/configure.zcml
imio/events/policy/browser/overrides/.gitkeep
imio/events/policy/browser/static/.gitkeep
imio/events/policy/profiles/default/actions.xml
imio/events/policy/profiles/default/browserlayer.xml
imio/events/policy/profiles/default/metadata.xml
imio/events/policy/profiles/default/viewlets.xml
imio/events/policy/profiles/default/registry/autopublishing.xml
imio/events/policy/profiles/default/registry/caching.xml
imio/events/policy/profiles/default/registry/events.xml
imio/events/policy/profiles/default/types/Collection.xml
imio/events/policy/profiles/default/types/Document.xml
imio/events/policy/profiles/default/types/Event.xml
imio/events/policy/profiles/default/types/File.xml
imio/events/policy/profiles/default/types/Folder.xml
imio/events/policy/profiles/default/types/Image.xml
imio/events/policy/profiles/default/types/Link.xml
imio/events/policy/profiles/default/types/News_Item.xml
imio/events/policy/profiles/default/types/Plone_site.xml
imio/events/policy/profiles/uninstall/browserlayer.xml
imio/events/policy/tests/__init__.py
imio/events/policy/tests/test_robot.py
imio/events/policy/tests/test_setup.py
imio/events/policy/tests/robot/test_example.robot
imio/events/policy/upgrades/__init__.py
imio/events/policy/upgrades/configure.zcml
imio/events/policy/upgrades/upgrades.py
imio/events/policy/upgrades/profiles/1000_to_1001/autopublishing.xml
imio/events/policy/upgrades/profiles/1001_to_1002/actions.xml
imio/events/policy/upgrades/profiles/1002_to_1003/registry/caching.xml
imio/events/policy/upgrades/profiles/1003_to_1004/registry/caching.xml
imio_events_policy-1.1.7.dist-info/licenses/LICENSE.GPL
imio_events_policy-1.1.7.dist-info/licenses/LICENSE.rst
imio_events_policy-1.1.7.dist-info/METADATA
imio_events_policy-1.1.7.dist-info/WHEEL
imio_events_policy-1.1.7.dist-info/namespace_packages.txt
imio_events_policy-1.1.7.dist-info/top_level.txt
imio_events_policy-1.1.7.dist-info/RECORD
