Metadata-Version: 2.4
Name: imio.events.policy
Version: 1.1.7
Summary: Policies to setup imio.events
Home-page: https://github.com/imio/imio.events.policy
Author: Christophe Boulanger
Author-email: christophe.boulanger@imio.be
License: GPL version 2
Project-URL: PyPI, https://pypi.python.org/pypi/imio.events.policy
Project-URL: Source, https://github.com/imio/imio.events.policy
Project-URL: Tracker, https://github.com/imio/imio.events.policy/issues
Keywords: Python Plone CMS
Classifier: Environment :: Web Environment
Classifier: Framework :: Plone
Classifier: Framework :: Plone :: Addon
Classifier: Framework :: Plone :: 6.0
Classifier: Framework :: Plone :: 6.1
Classifier: Programming Language :: Python
Classifier: Programming Language :: Python :: 3
Classifier: Programming Language :: Python :: 3.10
Classifier: Programming Language :: Python :: 3.11
Classifier: Programming Language :: Python :: 3.12
Classifier: Programming Language :: Python :: 3.13
Classifier: Operating System :: OS Independent
Classifier: License :: OSI Approved :: GNU General Public License v2 (GPLv2)
Requires-Python: >=3.10
License-File: LICENSE.GPL
License-File: LICENSE.rst
Requires-Dist: setuptools
Requires-Dist: z3c.jbot
Requires-Dist: plone.api>=1.8.4
Requires-Dist: plone.restapi
Requires-Dist: plone.app.dexterity
Requires-Dist: collective.autopublishing
Requires-Dist: collective.big.bang
Requires-Dist: collective.js.jqueryui
Requires-Dist: collective.messagesviewlet
Requires-Dist: collective.solr
Requires-Dist: collective.z3cform.select2
Requires-Dist: eea.facetednavigation
Requires-Dist: pas.plugins.imio
Requires-Dist: pas.plugins.kimug
Requires-Dist: imio.gdpr
Requires-Dist: imio.events.core
Requires-Dist: imio.smartweb.locales
Provides-Extra: test
Requires-Dist: plone.app.testing; extra == "test"
Requires-Dist: plone.testing>=5.0.0; extra == "test"
Requires-Dist: plone.app.contenttypes; extra == "test"
Requires-Dist: plone.app.robotframework[debug]; extra == "test"
Dynamic: author
Dynamic: author-email
Dynamic: classifier
Dynamic: description
Dynamic: home-page
Dynamic: keywords
Dynamic: license
Dynamic: license-file
Dynamic: project-url
Dynamic: provides-extra
Dynamic: requires-dist
Dynamic: requires-python
Dynamic: summary
